[
    {
        "id": 1,
        "category": "Web Design",
        "course_name": "Sonsing",
        "instructor_name": "Jonathan Clemoes",
        "duration": 20,
        "price": 4000,
        "rating": 4.2,
        "description": "justo sollicitudin ut suscipit a feugiat et eros vestibulum ac est lacinia nisi venenatis tristique fusce congue diam id ornare"
    },
    {
        "id": 2,
        "category": "Digital Marketing",
        "course_name": "Fintone",
        "instructor_name": "Corabella Fiennes",
        "duration": 5,
        "price": 1000,
        "rating": 3.4,
        "description": "nec dui luctus rutrum nulla tellus in sagittis dui vel nisl duis ac nibh fusce lacus purus aliquet"
    },
    {
        "id": 3,
        "category": "Excel",
        "course_name": "Voltsillam",
        "instructor_name": "Audry Rainsden",
        "duration": 14,
        "price": 2800,
        "rating": 3.3,
        "description": "mauris viverra diam vitae quam suspendisse potenti nullam porttitor lacus at turpis donec posuere"
    },
    {
        "id": 4,
        "category": "Excel",
        "course_name": "Subin",
        "instructor_name": "Gigi Belone",
        "duration": 5,
        "price": 1000,
        "rating": 2.9,
        "description": "turpis nec euismod scelerisque quam turpis adipiscing lorem vitae mattis nibh ligula nec sem"
    },
    {
        "id": 5,
        "category": "Development",
        "course_name": "Y-Solowarm",
        "instructor_name": "Beverlie Quarrie",
        "duration": 12,
        "price": 2400,
        "rating": 3.8,
        "description": "potenti in eleifend quam a odio in hac habitasse platea dictumst maecenas ut massa quis"
    },
    {
        "id": 6,
        "category": "Science",
        "course_name": "Bamity",
        "instructor_name": "Konstantin Delaprelle",
        "duration": 5,
        "price": 1000,
        "rating": 4.7,
        "description": "id lobortis convallis tortor risus dapibus augue vel accumsan tellus nisi eu orci mauris"
    },
    {
        "id": 7,
        "category": "Web Design",
        "course_name": "Greenlam",
        "instructor_name": "Consuelo Connop",
        "duration": 20,
        "price": 4000,
        "rating": 3.6,
        "description": "ridiculus mus vivamus vestibulum sagittis sapien cum sociis natoque penatibus et magnis dis"
    },
    {
        "id": 8,
        "category": "English",
        "course_name": "Zaam-Dox",
        "instructor_name": "Emlyn Leyman",
        "duration": 7,
        "price": 1400,
        "rating": 3.1,
        "description": "vestibulum quam sapien varius ut blandit non interdum in ante vestibulum ante ipsum primis in faucibus orci luctus et"
    },
    {
        "id": 9,
        "category": "Development",
        "course_name": "Solarbreeze",
        "instructor_name": "Fanni Madeley",
        "duration": 9,
        "price": 1800,
        "rating": 4.8,
        "description": "lectus in quam fringilla rhoncus mauris enim leo rhoncus sed"
    },
    {
        "id": 10,
        "category": "Web Design",
        "course_name": "Zontrax",
        "instructor_name": "Bale Ley",
        "duration": 16,
        "price": 3200,
        "rating": 4.3,
        "description": "morbi quis tortor id nulla ultrices aliquet maecenas leo odio condimentum id luctus nec molestie sed"
    },
    {
        "id": 11,
        "category": "Science",
        "course_name": "Veribet",
        "instructor_name": "Ado Clifforth",
        "duration": 9,
        "price": 1800,
        "rating": 2.8,
        "description": "nunc nisl duis bibendum felis sed interdum venenatis turpis enim blandit"
    },
    {
        "id": 12,
        "category": "Development",
        "course_name": "Solarbreeze",
        "instructor_name": "Dorrie Boother",
        "duration": 19,
        "price": 3800,
        "rating": 3.4,
        "description": "in sagittis dui vel nisl duis ac nibh fusce lacus purus aliquet at feugiat"
    },
    {
        "id": 13,
        "category": "Excel",
        "course_name": "Job",
        "instructor_name": "Gerrard Leupold",
        "duration": 15,
        "price": 3000,
        "rating": 3.6,
        "description": "massa id nisl venenatis lacinia aenean sit amet justo morbi ut odio cras mi pede malesuada"
    },
    {
        "id": 14,
        "category": "Excel",
        "course_name": "Span",
        "instructor_name": "Danya Fontin",
        "duration": 7,
        "price": 1400,
        "rating": 4.3,
        "description": "augue luctus tincidunt nulla mollis molestie lorem quisque ut erat curabitur gravida nisi at nibh in"
    },
    {
        "id": 15,
        "category": "English",
        "course_name": "Bitwolf",
        "instructor_name": "Mil Clemmow",
        "duration": 16,
        "price": 3200,
        "rating": 3.6,
        "description": "sollicitudin vitae consectetuer eget rutrum at lorem integer tincidunt ante vel ipsum praesent blandit lacinia erat vestibulum sed"
    },
    {
        "id": 16,
        "category": "English",
        "course_name": "Aerified",
        "instructor_name": "Adolf Slimings",
        "duration": 8,
        "price": 1600,
        "rating": 2.5,
        "description": "donec dapibus duis at velit eu est congue elementum in hac habitasse platea dictumst morbi vestibulum velit"
    }
]